_bcsv.cpython-314-x86_64-linux-musl.so
pybcsv/__init__.py
pybcsv/__version__.py
pybcsv/_version.py
pybcsv/bindings.cpp
pybcsv/pandas_utils.py
pybcsv/pandas_utils_original.py
pybcsv/py.typed
pybcsv.libs/libgcc_s-0cd532bd.so.1
pybcsv.libs/libstdc++-5d72f927.so.6.0.33
pybcsv-1.1.2.dist-info/METADATA
pybcsv-1.1.2.dist-info/WHEEL
pybcsv-1.1.2.dist-info/top_level.txt
pybcsv-1.1.2.dist-info/RECORD
