Metadata-Version: 2.4
Name: pybcsv
Version: 1.1.2
Summary: High-performance Python bindings for the BCSV (Binary CSV) library with pandas integration
Author: Tobias Weber
Author-email: Tobias Weber <weber.tobias.md@gmail.com>
Project-URL: Homepage, https://github.com/webertob/bcsv
Project-URL: Documentation, https://github.com/webertob/bcsv#readme
Project-URL: Repository, https://github.com/webertob/bcsv
Project-URL: Bug Tracker, https://github.com/webertob/bcsv/issues
Project-URL: Source Code, https://github.com/webertob/bcsv
Keywords: csv,binary,data-science,compression,performance,pandas,numpy,big-data,data-processing
Classifier: Development Status :: 4 - Beta
Classifier: Intended Audience :: Developers
Classifier: Intended Audience :: Science/Research
Classifier: Operating System :: OS Independent
Classifier: Programming Language :: C++
Classifier: Programming Language :: Python :: 3
Classifier: Programming Language :: Python :: 3.8
Classifier: Programming Language :: Python :: 3.9
Classifier: Programming Language :: Python :: 3.10
Classifier: Programming Language :: Python :: 3.11
Classifier: Programming Language :: Python :: 3.12
Classifier: Topic :: Scientific/Engineering
Classifier: Topic :: Software Development :: Libraries :: Python Modules
Classifier: Topic :: System :: Archiving :: Compression
Classifier: Topic :: Database
Classifier: Topic :: Scientific/Engineering :: Information Analysis
Requires-Python: >=3.12
Requires-Dist: numpy>=1.19.0
Provides-Extra: pandas
Requires-Dist: pandas>=1.0.0; extra == "pandas"
Provides-Extra: test
Requires-Dist: pytest>=6.0.0; extra == "test"
Requires-Dist: pytest-cov; extra == "test"
Provides-Extra: dev
Requires-Dist: pytest>=6.0.0; extra == "dev"
Requires-Dist: pytest-cov; extra == "dev"
Requires-Dist: black; extra == "dev"
Requires-Dist: flake8; extra == "dev"
Dynamic: author
Dynamic: requires-python
